cogment_lab/__init__.py
cogment_lab/constants.py
cogment_lab/core.py
cogment_lab/process_manager.py
cogment_lab/py.typed
cogment_lab/session_helpers.py
cogment_lab/version.py
cogment_lab/actors/__init__.py
cogment_lab/actors/configs.py
cogment_lab/actors/nn_actor.py
cogment_lab/actors/runner.py
cogment_lab/actors/simple.py
cogment_lab/cli/__init__.py
cogment_lab/cli/cli.py
cogment_lab/cli/download_cogment.py
cogment_lab/cli/launch.py
cogment_lab/envs/__init__.py
cogment_lab/envs/configs.py
cogment_lab/envs/gymnasium.py
cogment_lab/envs/pettingzoo.py
cogment_lab/envs/runner.py
cogment_lab/envs/conversions/__init__.py
cogment_lab/envs/conversions/observer.py
cogment_lab/envs/conversions/teacher.py
cogment_lab/generated/__init__.py
cogment_lab/generated/cog_settings.py
cogment_lab/generated/data_pb2.py
cogment_lab/generated/ndarray_pb2.py
cogment_lab/generated/spaces_pb2.py
cogment_lab/humans/__init__.py
cogment_lab/humans/actor.py
cogment_lab/humans/gradio_actor.py
cogment_lab/humans/runner.py
cogment_lab/humans/static/index.html
cogment_lab/protos/cogment.yaml
cogment_lab/protos/data.proto
cogment_lab/protos/ndarray.proto
cogment_lab/protos/spaces.proto
cogment_lab/specs/__init__.py
cogment_lab/specs/action_space.py
cogment_lab/specs/encode_rendered_frame.py
cogment_lab/specs/environment_specs.py
cogment_lab/specs/ndarray_serialization.py
cogment_lab/specs/observation_space.py
cogment_lab/specs/spaces_serialization.py
cogment_lab/utils/__init__.py
cogment_lab/utils/coltra_utils.py
cogment_lab/utils/grpc.py
cogment_lab/utils/import_class.py
cogment_lab/utils/runners.py
cogment_lab/utils/trial_utils.py
cogment_lab/utils/yaml_utils.py
cogment_lab-0.1.5.dist-info/METADATA
cogment_lab-0.1.5.dist-info/WHEEL
cogment_lab-0.1.5.dist-info/entry_points.txt
cogment_lab-0.1.5.dist-info/licenses/LICENSE
cogment_lab-0.1.5.dist-info/RECORD
