Metadata-Version: 2.3
Name: cogment_lab
Version: 0.1.5
Project-URL: Homepage, https://cogment.ai/lab
Project-URL: Repository, https://github.com/cogment/cogment-lab
Project-URL: Documentation, https://cogment.ai/lab
Project-URL: Bug Report, https://github.com/cogment/cogment-lab/issues
License-Expression: Apache-2.0
License-File: LICENSE
Keywords: AI,HILL,RL,Reinforcement Learning,human-in-the-loop
Classifier: Development Status :: 4 - Beta
Classifier: Intended Audience :: Science/Research
Classifier: License :: OSI Approved :: Apache Software License
Classifier: Programming Language :: Python :: 3
Classifier: Programming Language :: Python :: 3.8
Classifier: Programming Language :: Python :: 3.9
Classifier: Programming Language :: Python :: 3.10
Classifier: Topic :: Scientific/Engineering :: Artificial Intelligence
Requires-Dist: cogment[generate]<3.0.0,>=2.10.1
Requires-Dist: fastapi>=0.103
Requires-Dist: grpcio-tools>=1.48
Requires-Dist: grpcio>=1.48
Requires-Dist: gymnasium[classic-control]~=0.29
Requires-Dist: jinja2>=3.1
Requires-Dist: numpy
Requires-Dist: pettingzoo~=1.23.1
Requires-Dist: pillow>=9.0
Requires-Dist: pyyaml>=5.0
Requires-Dist: starlette>=0.21.0
Requires-Dist: tqdm
Requires-Dist: uvicorn[standard]>=0.17.6
Provides-Extra: all
Requires-Dist: coltra>=0.2.1; extra == 'all'
Requires-Dist: hatch>=1.7.0; extra == 'all'
Requires-Dist: jupyter>=1.0.0; extra == 'all'
Requires-Dist: jupyterlab>=3.5.3; extra == 'all'
Requires-Dist: matplotlib; extra == 'all'
Requires-Dist: pytest-asyncio; extra == 'all'
Requires-Dist: pytest>=7.1.3; extra == 'all'
Requires-Dist: ruff>=0.1.7; extra == 'all'
Requires-Dist: torch; extra == 'all'
Requires-Dist: wandb>=0.13.9; extra == 'all'
Provides-Extra: coltra
Requires-Dist: coltra>=0.2.1; extra == 'coltra'
Requires-Dist: torch; extra == 'coltra'
Requires-Dist: wandb>=0.13.9; extra == 'coltra'
Provides-Extra: dev
Requires-Dist: hatch>=1.7.0; extra == 'dev'
Requires-Dist: pytest-asyncio; extra == 'dev'
Requires-Dist: pytest>=7.1.3; extra == 'dev'
Requires-Dist: ruff>=0.1.7; extra == 'dev'
